UliEngineering/Chemistry/Absorption.py
UliEngineering/Chemistry/DNARNA.py
UliEngineering/Chemistry/__init__.py
UliEngineering/Economics/Interest.py
UliEngineering/Economics/__init__.py
UliEngineering/Electronics/Capacitors.py
UliEngineering/Electronics/Crystal.py
UliEngineering/Electronics/Filter.py
UliEngineering/Electronics/Hysteresis.py
UliEngineering/Electronics/Inductors.py
UliEngineering/Electronics/LED.py
UliEngineering/Electronics/LogarithmicAmplifier.py
UliEngineering/Electronics/MOSFET.py
UliEngineering/Electronics/Microstrip.py
UliEngineering/Electronics/OpAmp.py
UliEngineering/Electronics/Power.py
UliEngineering/Electronics/PowerFactor.py
UliEngineering/Electronics/PropagationSpeed.py
UliEngineering/Electronics/Reactance.py
UliEngineering/Electronics/ResistorSelection.py
UliEngineering/Electronics/Resistors.py
UliEngineering/Electronics/SwitchingRegulator.py
UliEngineering/Electronics/TemperatureCoefficient.py
UliEngineering/Electronics/Thermistor.py
UliEngineering/Electronics/Tolerance.py
UliEngineering/Electronics/VoltageDivider.py
UliEngineering/Electronics/ZenerDiode.py
UliEngineering/Electronics/__init__.py
UliEngineering/EngineerIO/Area.py
UliEngineering/EngineerIO/Concentration.py
UliEngineering/EngineerIO/Decorators.py
UliEngineering/EngineerIO/Defaults.py
UliEngineering/EngineerIO/Length.py
UliEngineering/EngineerIO/Timespan.py
UliEngineering/EngineerIO/Types.py
UliEngineering/EngineerIO/UnitInfo.py
UliEngineering/EngineerIO/Volume.py
UliEngineering/EngineerIO/__init__.py
UliEngineering/Exceptions.py
UliEngineering/Filesystem/Hash.py
UliEngineering/Filesystem/__init__.py
UliEngineering/Math/Coordinates.py
UliEngineering/Math/Decibel.py
UliEngineering/Math/Geometry/Circle.py
UliEngineering/Math/Geometry/Cylinder.py
UliEngineering/Math/Geometry/Polygon.py
UliEngineering/Math/Geometry/Sphere.py
UliEngineering/Math/Geometry/__init__.py
UliEngineering/Math/__init__.py
UliEngineering/Mechanics/Threads.py
UliEngineering/Mechanics/__init__.py
uliengineering-1.1.2.dist-info/METADATA
uliengineering-1.1.2.dist-info/WHEEL
uliengineering-1.1.2.dist-info/licenses/LICENSE
uliengineering-1.1.2.dist-info/RECORD
