Metadata-Version: 2.4
Name: UliEngineering
Version: 1.1.2
Summary: Computational tools for electronics engineering
License: Apache-2.0
License-File: LICENSE
Keywords: electronics,engineering,computational tools
Author: Uli Köhler
Author-email: ukoehler@techoverflow.net
Requires-Python: >=3.0
Classifier: Development Status :: 5 - Production/Stable
Classifier: Intended Audience :: Developers
Classifier: Intended Audience :: Education
Classifier: Intended Audience :: Information Technology
Classifier: Intended Audience :: Science/Research
Classifier: License :: DFSG approved
Classifier: License :: OSI Approved :: Apache Software License
Classifier: Programming Language :: Python
Classifier: Programming Language :: Python :: 3
Classifier: Programming Language :: Python :: 3.4
Classifier: Programming Language :: Python :: 3.5
Classifier: Programming Language :: Python :: 3.6
Classifier: Programming Language :: Python :: 3.7
Classifier: Programming Language :: Python :: 3.8
Classifier: Programming Language :: Python :: 3.9
Classifier: Programming Language :: Python :: 3.10
Classifier: Programming Language :: Python :: 3.11
Classifier: Programming Language :: Python :: 3.12
Classifier: Programming Language :: Python :: 3.13
Classifier: Programming Language :: Python :: 3.14
Classifier: Topic :: Scientific/Engineering
Classifier: Topic :: Scientific/Engineering :: Bio-Informatics
Classifier: Topic :: Scientific/Engineering :: Electronic Design Automation (EDA)
Classifier: Topic :: Scientific/Engineering :: Information Analysis
Classifier: Topic :: Scientific/Engineering :: Physics
Requires-Dist: numpy (>=1.5)
Requires-Dist: toolz (>=0.5)
Project-URL: Homepage, https://techoverflow.net/
